diskcache_rs-0.4.5.dist-info/METADATA
diskcache_rs-0.4.5.dist-info/WHEEL
diskcache_rs-0.4.5.dist-info/licenses/LICENSE
diskcache_rs/__init__.py
diskcache_rs/__init__.pyi
diskcache_rs/_diskcache_rs.pyi
diskcache_rs/_diskcache_rs.pypy311-pp73-aarch64-linux-gnu.so
diskcache_rs/cache.py
diskcache_rs/core.py
diskcache_rs/fast_cache.py
diskcache_rs/pickle_cache.py
diskcache_rs/rust_pickle.py
diskcache_rs-0.4.5.dist-info/RECORD
