Metadata-Version: 2.4
Name: diskcache_rs
Version: 0.4.5
Classifier: Development Status :: 4 - Beta
Classifier: Intended Audience :: Developers
Classifier: License :: OSI Approved :: Apache Software License
Classifier: Programming Language :: Rust
Classifier: Programming Language :: Python :: Implementation :: CPython
Classifier: Programming Language :: Python :: Implementation :: PyPy
Classifier: Programming Language :: Python :: 3
Classifier: Programming Language :: Python :: 3.8
Classifier: Programming Language :: Python :: 3.9
Classifier: Programming Language :: Python :: 3.10
Classifier: Programming Language :: Python :: 3.11
Classifier: Programming Language :: Python :: 3.12
Classifier: Programming Language :: Python :: 3.13
Classifier: Topic :: Database
Classifier: Topic :: Software Development :: Libraries :: Python Modules
Classifier: Topic :: System :: Archiving
Requires-Dist: importlib-metadata>=1.0 ; python_full_version < '3.8'
License-File: LICENSE
Summary: A high-performance disk cache implementation in Rust with Python bindings
Keywords: cache,disk,storage,performance,rust
Author-email: longhao <hal.long@outlook.com>
License: Apache-2.0
Requires-Python: >=3.8
Project-URL: Homepage, https://github.com/loonghao/diskcache_rs
Project-URL: Repository, https://github.com/loonghao/diskcache_rs
Project-URL: Documentation, https://github.com/loonghao/diskcache_rs
Project-URL: Bug Tracker, https://github.com/loonghao/diskcache_rs/issues
